LICENSE
MANIFEST.in
README.md
setup.py
liamcloud/__init__.py
liamcloud/mqtt.py
liamcloud/robot.py
liamcloud.egg-info/PKG-INFO
liamcloud.egg-info/SOURCES.txt
liamcloud.egg-info/dependency_links.txt
liamcloud.egg-info/requires.txt
liamcloud.egg-info/top_level.txt