Metadata-Version: 2.1
Name: liamcloud
Version: 1.0.1
Summary: 云服务
Home-page: https://github.com/py-liam/liamcloud
Author: liam
Author-email: 37907909@qq.com
License: MIT
Platform: all
Classifier: License :: OSI Approved :: MIT License
Classifier: Programming Language :: Python
Classifier: Programming Language :: Python :: 3
Classifier: Programming Language :: Python :: 3.6
Classifier: Programming Language :: Python :: Implementation :: CPython
Classifier: Programming Language :: Python :: Implementation :: PyPy
Requires-Python: >=3.6.0
